back/__init__.py
back/bone.py
back/utils.py
back-0.1.4.dist-info/LICENSE
back-0.1.4.dist-info/METADATA
back-0.1.4.dist-info/WHEEL
back-0.1.4.dist-info/top_level.txt
back-0.1.4.dist-info/RECORD
