Metadata-Version: 2.1
Name: back
Version: 0.1.4
Summary: Backbone for PyTorch training loop
Home-page: https://github.com/EvgenyKashin/backbone
Author: Evgeny Kashin
Author-email: kashinevge@gmail.com
License: MIT
Keywords: pytorch,deep-learning,training-loop,backbone
Platform: UNKNOWN
Requires-Python: >=3.7.0
